langbrainscore/__init__.py
langbrainscore/__main__.py
langbrainscore/dataset/__init__.py
langbrainscore/dataset/dataset.py
langbrainscore/encoder/__init__.py
langbrainscore/encoder/ann.py
langbrainscore/encoder/brain.py
langbrainscore/interface/__init__.py
langbrainscore/interface/encoder.py
langbrainscore/mapping/__init__.py
langbrainscore/mapping/rdm.py
langbrainscore/mapping/ridge.py
langbrainscore/metrics/__init__.py
langbrainscore/metrics/kendall_tau.py
langbrainscore/metrics/pearson_r.py
langbrainscore/metrics/rank_acc.py
langbrainscore/metrics/spearman_rho.py
langbrainscore/utils/.gitkeep
langbrainscore/utils/__init__.py
langbrainscore/utils/cache_utils.py
langbrainscore/utils/encoder_utils.py
langbrainscore/utils/logging.py
langbrainscore/utils/s3_utils.py
langbrainscore/utils/stim_utils.py
langbrainscore-0.1.0.dist-info/LICENSE
langbrainscore-0.1.0.dist-info/WHEEL
langbrainscore-0.1.0.dist-info/METADATA
langbrainscore-0.1.0.dist-info/RECORD
